invoke_plugin_for_sphinx/__init__.py
invoke_plugin_for_sphinx/_plugin.py
invoke_plugin_for_sphinx/py.typed
invoke_plugin_for_sphinx-4.0.0.dist-info/licenses/LICENSE
invoke_plugin_for_sphinx-4.0.0.dist-info/METADATA
invoke_plugin_for_sphinx-4.0.0.dist-info/WHEEL
invoke_plugin_for_sphinx-4.0.0.dist-info/top_level.txt
invoke_plugin_for_sphinx-4.0.0.dist-info/RECORD
