Metadata-Version: 2.4
Name: invoke-plugin-for-sphinx
Version: 4.0.0
Summary: Sphinx plugin which can render invoke tasks with autodoc
Author-email: Kai Harder <kai.harder@sap.com>
License-Expression: Apache-2.0
Project-URL: Changelog, https://github.com/SAP/invoke-plugin-for-sphinx/blob/main/CHANGELOG.md
Project-URL: Issue Tracker, https://github.com/SAP/invoke-plugin-for-sphinx/issues
Keywords: sphinx,invoke,plugin,inv,documentation
Classifier: Development Status :: 5 - Production/Stable
Classifier: Environment :: Plugins
Classifier: Framework :: Sphinx :: Extension
Classifier: Intended Audience :: Developers
Classifier: Natural Language :: English
Classifier: Operating System :: OS Independent
Classifier: Programming Language :: Python :: 3
Classifier: Programming Language :: Python :: 3 :: Only
Classifier: Programming Language :: Python :: 3.10
Classifier: Programming Language :: Python :: 3.11
Classifier: Programming Language :: Python :: 3.12
Classifier: Programming Language :: Python :: 3.13
Classifier: Programming Language :: Python :: 3.14
Classifier: Topic :: Documentation
Classifier: Topic :: Documentation :: Sphinx
Classifier: Typing :: Typed
Requires-Python: <4,>=3.10
License-File: LICENSE
Requires-Dist: sphinx<9,>=7
Requires-Dist: invoke<3,>=2.1
Requires-Dist: typing-extensions~=4.4
Dynamic: license-file
